.editorconfig
.travis.yml
AUTHORS.rst
CHANGELOG.rst
CONTRIBUTING.rst
MANIFEST.in
README.rst
requirements.txt
setup.py
tox.ini
docs/Makefile
docs/authors.rst
docs/changelog.rst
docs/conf.py
docs/contributing.rst
docs/index.rst
docs/license.rst
docs/make.bat
docs/readme.rst
docs/requirements.txt
orbitant/__init__.py
orbitant/bpmfinder.py
orbitant/generator.py
orbitant/transport.py
orbitant.egg-info/PKG-INFO
orbitant.egg-info/SOURCES.txt
orbitant.egg-info/dependency_links.txt
orbitant.egg-info/not-zip-safe
orbitant.egg-info/requires.txt
orbitant.egg-info/top_level.txt
orbitant/tools/__init__.py
orbitant/tools/bpmfinder.py
orbitant/tools/generator.py
requirements/base.txt
requirements/tests.txt
tests/test_placeholder.py